LICENSE
MANIFEST.in
README.md
requirements.txt
setup.cfg
setup.py
bravaorm/__init__.py
bravaorm.egg-info/PKG-INFO
bravaorm.egg-info/SOURCES.txt
bravaorm.egg-info/__init__.py
bravaorm.egg-info/dependency_links.txt
bravaorm.egg-info/requires.txt
bravaorm.egg-info/top_level.txt
bravaorm/context/__init__.py
bravaorm/context/connection.py
bravaorm/context/database.py
bravaorm/entity/__init__.py
bravaorm/entity/datatype.py
bravaorm/entity/entity.py
bravaorm/utils/__init__.py
bravaorm/utils/angular.py
bravaorm/utils/make.py
bravaorm/utils/inflector/__init__.py
bravaorm/utils/inflector/languages/__init__.py
bravaorm/utils/inflector/languages/base.py
bravaorm/utils/inflector/languages/english.py
bravaorm/utils/inflector/languages/portuguese.py
bravaorm/utils/inflector/languages/spanish.py
bravaorm/utils/log/__init__.py
bravaorm/utils/log/colored_log.py
bravaorm/utils/log/colors.py
test/test.py