Metadata-Version: 2.1
Name: bravaorm
Version: 0.0.29
Summary: Python ORM for MySQL
Home-page: https://github.com/robertons/bravaorm
Author: Roberto Neves
Author-email: robertonsilva@gmail.com
License: MIT
Keywords: orm,datamodel,database,model,entity,sdk,mysql,mariadb
Platform: UNKNOWN
Classifier: Development Status :: 3 - Alpha
Classifier: Environment :: Web Environment
Classifier: Intended Audience :: Developers
Classifier: Natural Language :: Portuguese (Brazilian)
Classifier: License :: OSI Approved :: MIT License
Classifier: Programming Language :: Python :: 3.6
License-File: LICENSE
